sqnethelper/ConfigManager.py
sqnethelper/ECSManager.py
sqnethelper/ShellHelper.py
sqnethelper/SqLog.py
sqnethelper/SqNetHelper.py
sqnethelper/SqUtils.py
sqnethelper/VPCManager.py
sqnethelper/__init__.py
sqnethelper/__main__.py
sqnethelper/cli.py
sqnethelper/resources.py
sqnethelper/sing-box_template.json
sqnethelper-0.4.0.dist-info/METADATA
sqnethelper-0.4.0.dist-info/WHEEL
sqnethelper-0.4.0.dist-info/entry_points.txt
sqnethelper-0.4.0.dist-info/top_level.txt
sqnethelper-0.4.0.dist-info/RECORD
