Metadata-Version: 2.4
Name: sqnethelper
Version: 0.4.0
Summary: A command line tool to manage Alibaba Cloud ECS instances
Author: weisq
Author-email: weishqdev@gmail.com
Classifier: Programming Language :: Python :: 3
Classifier: Operating System :: OS Independent
Requires-Python: >=3.6
Requires-Dist: aliyun-python-sdk-core
Requires-Dist: aliyun-python-sdk-ecs
Requires-Dist: aliyun-python-sdk-vpc
Requires-Dist: bcrypt
Requires-Dist: cffi
Requires-Dist: click
Requires-Dist: cryptography
Requires-Dist: jmespath
Requires-Dist: paramiko
Requires-Dist: pycparser
Requires-Dist: PyNaCl
Requires-Dist: websockets
Dynamic: author
Dynamic: author-email
Dynamic: classifier
Dynamic: description
Dynamic: description-content-type
Dynamic: requires-dist
Dynamic: requires-python
Dynamic: summary
